plusplus/__init__.py
plusplus/patching.py
plusplus/wrappers.py
plusplus-0.1.post1.dist-info/LICENSE
plusplus-0.1.post1.dist-info/METADATA
plusplus-0.1.post1.dist-info/WHEEL
plusplus-0.1.post1.dist-info/top_level.txt
plusplus-0.1.post1.dist-info/RECORD
