Metadata-Version: 2.1
Name: plusplus
Version: 0.1.post1
Summary: Enable the ++x and --x expressions in Python
Home-page: https://github.com/borzunov/plusplus
Author: Alexander Borzunov
Author-email: borzunov.alexander@gmail.com
License: UNKNOWN
Project-URL: Bug Tracker, https://github.com/borzunov/plusplus/issues
Platform: UNKNOWN
Classifier: Programming Language :: Python :: 3
Classifier: License :: OSI Approved :: MIT License
Classifier: Operating System :: OS Independent
Requires-Python: >=3.6
License-File: LICENSE
Requires-Dist: bytecode (>=0.12.0)
Provides-Extra: dev
Requires-Dist: pytest ; extra == 'dev'
Requires-Dist: pytest-cov ; extra == 'dev'
